sanic_openapi/__init__.py
sanic_openapi/autodoc.py
sanic_openapi/utils.py
sanic_openapi/openapi2/__init__.py
sanic_openapi/openapi2/api.py
sanic_openapi/openapi2/blueprint.py
sanic_openapi/openapi2/doc.py
sanic_openapi/openapi2/spec.py
sanic_openapi/openapi3/__init__.py
sanic_openapi/openapi3/blueprint.py
sanic_openapi/openapi3/builders.py
sanic_openapi/openapi3/definitions.py
sanic_openapi/openapi3/openapi.py
sanic_openapi/openapi3/types.py
sanic_openapi/ui/README.md
sanic_openapi/ui/favicon-16x16.png
sanic_openapi/ui/favicon-32x32.png
sanic_openapi/ui/index.html
sanic_openapi/ui/oauth2-redirect.html
sanic_openapi/ui/swagger-ui-bundle.js
sanic_openapi/ui/swagger-ui-bundle.js.map
sanic_openapi/ui/swagger-ui-es-bundle-core.js
sanic_openapi/ui/swagger-ui-es-bundle-core.js.map
sanic_openapi/ui/swagger-ui-es-bundle.js
sanic_openapi/ui/swagger-ui-es-bundle.js.map
sanic_openapi/ui/swagger-ui-standalone-preset.js
sanic_openapi/ui/swagger-ui-standalone-preset.js.map
sanic_openapi/ui/swagger-ui.css
sanic_openapi/ui/swagger-ui.css.map
sanic_openapi/ui/swagger-ui.js
sanic_openapi/ui/swagger-ui.js.map
sanic_openapi-21.12.0.dist-info/LICENSE
sanic_openapi-21.12.0.dist-info/METADATA
sanic_openapi-21.12.0.dist-info/WHEEL
sanic_openapi-21.12.0.dist-info/top_level.txt
sanic_openapi-21.12.0.dist-info/RECORD
