Metadata-Version: 2.1
Name: sanic-openapi
Version: 21.12.0
Summary: Easily document your Sanic API with a UI.
Home-page: http://github.com/sanic-org/sanic-openapi/
Author: Sanic Community
License: MIT
Platform: any
Classifier: Development Status :: 4 - Beta
Classifier: Environment :: Web Environment
Classifier: License :: OSI Approved :: MIT License
Classifier: Programming Language :: Python :: 3.7
Classifier: Programming Language :: Python :: 3.8
Classifier: Programming Language :: Python :: 3.9
Provides-Extra: dev
Provides-Extra: test
Provides-Extra: doc
License-File: LICENSE
